smplx/__init__.py
smplx/body_models.py
smplx/joint_names.py
smplx/lbs.py
smplx/utils.py
smplx/vertex_ids.py
smplx/vertex_joint_selector.py
smplx-0.1.28.dist-info/LICENSE
smplx-0.1.28.dist-info/METADATA
smplx-0.1.28.dist-info/WHEEL
smplx-0.1.28.dist-info/top_level.txt
smplx-0.1.28.dist-info/RECORD
