Metadata-Version: 2.1
Name: smplx
Version: 0.1.28
Summary: PyTorch module for loading the SMPLX body model
Home-page: http://smpl-x.is.tuebingen.mpg.de
Author: Vassilis Choutas
Author-email: vassilis.choutas@tuebingen.mpg.de
License: UNKNOWN
Platform: UNKNOWN
Requires-Python: >=3.6.0
Provides-Extra: pyrender
Provides-Extra: open3d
Provides-Extra: matplotlib
Provides-Extra: all
